trasor/__init__.py
trasor/async_client.py
trasor/client.py
trasor/client_original.py
trasor/exceptions.py
trasor/integrations/__init__.py
trasor/integrations/crewai.py
trasor/integrations/langchain.py
trasor_sdk-2.1.0.dist-info/METADATA
trasor_sdk-2.1.0.dist-info/WHEEL
trasor_sdk-2.1.0.dist-info/top_level.txt
trasor_sdk-2.1.0.dist-info/RECORD
