Metadata-Version: 2.4
Name: trasor-sdk
Version: 2.1.0
Summary: Official Python SDK for Trasor.io trust infrastructure platform
Home-page: https://github.com/trasor-io/trasor-python
Author: Trasor.io
Author-email: "Trasor.io" <support@trasor.io>
Maintainer-email: "Trasor.io" <support@trasor.io>
License-Expression: MIT
Project-URL: Homepage, https://trasor.io
Project-URL: Documentation, https://docs.trasor.io/sdk/python
Project-URL: Repository, https://github.com/trasor-io/trasor-python
Project-URL: Bug Tracker, https://github.com/trasor-io/trasor-python/issues
Project-URL: API Reference, https://docs.trasor.io/api
Keywords: audit,logging,security,ai,agents,blockchain,verification,trust,infrastructure
Classifier: Development Status :: 5 - Production/Stable
Classifier: Intended Audience :: Developers
Classifier: Topic :: Software Development :: Libraries :: Python Modules
Classifier: Topic :: System :: Logging
Classifier: Topic :: Security
Classifier: Programming Language :: Python :: 3
Classifier: Programming Language :: Python :: 3.8
Classifier: Programming Language :: Python :: 3.9
Classifier: Programming Language :: Python :: 3.10
Classifier: Programming Language :: Python :: 3.11
Classifier: Programming Language :: Python :: 3.12
Classifier: Operating System :: OS Independent
Requires-Python: >=3.8.1
Requires-Dist: requests>=2.25.0
Provides-Extra: dev
Requires-Dist: pytest>=6.0; extra == "dev"
Requires-Dist: pytest-cov>=2.0; extra == "dev"
Requires-Dist: black>=21.0; extra == "dev"
Requires-Dist: flake8>=3.8; extra == "dev"
Requires-Dist: mypy>=0.812; extra == "dev"
Provides-Extra: async
Requires-Dist: aiohttp>=3.8.0; extra == "async"
Provides-Extra: crewai
Requires-Dist: crewai>=0.1.0; extra == "crewai"
Provides-Extra: langchain
Requires-Dist: langchain>=0.0.200; extra == "langchain"
Provides-Extra: all
Requires-Dist: aiohttp>=3.8.0; extra == "all"
Requires-Dist: crewai>=0.1.0; extra == "all"
Requires-Dist: langchain>=0.0.200; extra == "all"
Dynamic: author
Dynamic: home-page
Dynamic: requires-python
